{
  "db_name": "PostgreSQL",
  "query": "\n        INSERT INTO blocks (number, hash, parent_hash, timestamp, extrinsics_count, events_count)\n        VALUES ($1, $2, $3, $4, $5, $6)\n        ON CONFLICT (number) DO NOTHING\n        ",
  "describe": {
    "columns": [],
    "parameters": {
      "Left": [
        "Int8",
        "Varchar",
        "Varchar",
        "Timestamptz",
        "Int4",
        "Int4"
      ]
    },
    "nullable": []
  },
  "hash": "94c213766b1c6a1b29a272e46a4a9e5e1a0cc6554c61fa95ff2bc6bb2dd76d63"
}
